mcp_defender/__init__.py
mcp_defender/server.py
mcp_msdefenderkql-1.0.0.dist-info/METADATA
mcp_msdefenderkql-1.0.0.dist-info/WHEEL
mcp_msdefenderkql-1.0.0.dist-info/entry_points.txt
mcp_msdefenderkql-1.0.0.dist-info/licenses/LICENSE
mcp_msdefenderkql-1.0.0.dist-info/RECORD
