Metadata-Version: 2.4
Name: mcp-msdefenderkql
Version: 1.0.0
Summary: MCP server for Microsoft Defender Advanced Hunting - execute KQL queries via natural language
Project-URL: Homepage, https://github.com/trickyfalcon/mcp-defender
Project-URL: Repository, https://github.com/trickyfalcon/mcp-defender
Project-URL: Issues, https://github.com/trickyfalcon/mcp-defender/issues
Author-email: trickyfalcon <trickyfalcon@users.noreply.github.com>
License-Expression: MIT
License-File: LICENSE
Keywords: advanced-hunting,kql,mcp,microsoft-defender,model-context-protocol,security,siem,threat-hunting
Classifier: Development Status :: 4 - Beta
Classifier: Intended Audience :: Developers
Classifier: Intended Audience :: Information Technology
Classifier: Intended Audience :: System Administrators
Classifier: License :: OSI Approved :: MIT License
Classifier: Operating System :: OS Independent
Classifier: Programming Language :: Python :: 3
Classifier: Programming Language :: Python :: 3.10
Classifier: Programming Language :: Python :: 3.11
Classifier: Programming Language :: Python :: 3.12
Classifier: Topic :: Security
Classifier: Topic :: System :: Systems Administration
Requires-Python: >=3.10
Requires-Dist: azure-identity>=1.15.0
Requires-Dist: httpx>=0.27.0
Requires-Dist: mcp>=1.0.0
Requires-Dist: python-dotenv>=1.0.0
Provides-Extra: dev
Requires-Dist: bandit>=1.7.0; extra == 'dev'
Requires-Dist: mypy>=1.9.0; extra == 'dev'
Requires-Dist: pytest-asyncio>=0.23.0; extra == 'dev'
Requires-Dist: pytest>=8.0.0; extra == 'dev'
Requires-Dist: ruff>=0.3.0; extra == 'dev'
